aq_lib/__init__.py
aq_lib/configuration/__init__.py
aq_lib/configuration/configuration.py
aq_lib/event/__init__.py
aq_lib/event/event.py
aq_lib/event/event_mapper.py
aq_lib/event/event_type.py
aq_lib/manager/__init__.py
aq_lib/manager/handler.py
aq_lib/manager/httpclient.py
aq_lib/manager/public_handler.py
aq_lib/manager/wsclient.py
aq_lib/model/__init__.py
aq_lib/model/exec_type.py
aq_lib/model/md_entry.py
aq_lib/model/md_entry_type.py
aq_lib/model/md_subscription_type.py
aq_lib/model/order_status.py
aq_lib/model/strategy_status.py
aq_lib/transport/__init__.py
aq_lib/transport/serializable.py
aq_lib/utils/__init__.py
aq_lib/utils/async_logging_handler.py
aq_lib/utils/byte_utils.py
aq_lib/utils/logger.py
aq_lib-0.0.11.dist-info/METADATA
aq_lib-0.0.11.dist-info/WHEEL
aq_lib-0.0.11.dist-info/top_level.txt
aq_lib-0.0.11.dist-info/RECORD
