Metadata-Version: 2.1
Name: aq-lib
Version: 0.0.11
Summary: public lib for arquants
Home-page: https://gitlab.com/arquants/aq-lib.git
Author: ArQuants
Author-email: info@arquants.trading
License: MIT
Platform: UNKNOWN
Requires-Dist: amqp (==2.2.2)
Requires-Dist: enum34 (==1.1.6)
Requires-Dist: jsonpickle (==0.9.5)
Requires-Dist: kombu (==4.2.1)
Requires-Dist: vine (==1.1.4)
Requires-Dist: redis (==2.10.6)
Requires-Dist: requests (==2.22.0)
